plottags
