Metadata-Version: 1.1
Name: plottags
Version: 0.1.2
Summary: A package for plotting the tag history of repositories
Home-page: https://github.com/logston/plottags
Author: Paul Logston
Author-email: code@logston.me
License: Copyright (c) 2015, Paul Logston
